hdw_tools/__init__.py
hdw_tools/core/__init__.py
hdw_tools/core/base.py
hdw_tools/core/config.py
hdw_tools/core/models.py
hdw_tools/tools/__init__.py
hdw_tools/tools/crewai_linkedin.py
hdw_tools/tools/llama_linkedin.py
hdw_tools-0.0.6.dist-info/LICENSE
hdw_tools-0.0.6.dist-info/METADATA
hdw_tools-0.0.6.dist-info/WHEEL
hdw_tools-0.0.6.dist-info/top_level.txt
hdw_tools-0.0.6.dist-info/RECORD
