Metadata-Version: 2.2
Name: hdw_tools
Version: 0.0.6
Summary: Horizon Data Wave Tools
Home-page: https://github.com/horizondatawave/hdw-tools
Author: HorizonDataWave
Author-email: pip@horizondatawave.ai
License: MIT
Requires-Python: >=3.12
License-File: LICENSE
Requires-Dist: requests~=2.32.3
Requires-Dist: llama-index-core~=0.11.22
Requires-Dist: pydantic~=2.10.5
Requires-Dist: pydantic-settings~=2.6.1
Requires-Dist: crewai-tools~=0.25.8
Dynamic: author
Dynamic: author-email
Dynamic: description
Dynamic: description-content-type
Dynamic: home-page
Dynamic: license
Dynamic: requires-dist
Dynamic: requires-python
Dynamic: summary
